{
  "type": "FeatureCollection", 
  "features": [
    {
      "geometry": {
        "type": "Polygon", 
        "coordinates": [
          [
            [
              75.99187869660258, 
              61.177299709713424
            ], 
            [
              75.99187869660258, 
              61.177299709713424
            ], 
            [
              76.00924197785267, 
              61.18763499617181
            ], 
            [
              76.00996544790476, 
              61.19233755151036
            ], 
            [
              76.00810509634223, 
              61.205670071041666
            ], 
            [
              76.00924197785267, 
              61.20985586205731
            ], 
            [
              76.02143761587354, 
              61.21959686954433
            ], 
            [
              76.03146284373818, 
              61.23202505151052
            ], 
            [
              76.03177290233191, 
              61.23450552026054
            ], 
            [
              76.03084272655067, 
              61.24096507429702
            ], 
            [
              76.03146284373818, 
              61.24318716088557
            ], 
            [
              76.03363325389444, 
              61.24344554304703
            ], 
            [
              76.0407646015507, 
              61.24277374942723
            ], 
            [
              76.0426249531132, 
              61.24318716088557
            ], 
            [
              76.03094607941526, 
              61.2741930202607
            ], 
            [
              76.03146284373818, 
              61.28760305444044
            ], 
            [
              76.0364237812382, 
              61.292228095130554
            ], 
            [
              76.04479536326949, 
              61.29610382755244
            ], 
            [
              76.05192671092576, 
              61.30137482364621
            ], 
            [
              76.05368370962367, 
              61.30987559675823
            ], 
            [
              76.08148563019671, 
              61.30716258406291
            ], 
            [
              76.1170390156135, 
              61.28147939721384
            ], 
            [
              76.1425671731657, 
              61.27651845971383
            ], 
            [
              76.14153364451985, 
              61.24964671492205
            ], 
            [
              76.12706424347815, 
              61.23254181583344
            ], 
            [
              76.10918419790514, 
              61.217969061927135
            ], 
            [
              76.0981254413947, 
              61.19874542911455
            ], 
            [
              76.09771202993636, 
              61.18623973249993
            ], 
            [
              76.10918419790514, 
              61.14319326440079
            ], 
            [
              76.07538781118626, 
              61.143658352291425
            ], 
            [
              76.06422570181121, 
              61.138180650468485
            ], 
            [
              76.06474246613413, 
              61.12097239851529
            ], 
            [
              76.08324262889462, 
              61.10743317325482
            ], 
            [
              76.10267296743638, 
              61.11384105085901
            ], 
            [
              76.12251671743644, 
              61.12660512963511
            ], 
            [
              76.1425671731657, 
              61.132082831458035
            ], 
            [
              76.14287723175946, 
              61.11740672468714
            ], 
            [
              76.15982710155117, 
              61.09792470971311
            ], 
            [
              76.16478803905122, 
              61.08766693790318
            ], 
            [
              76.16416792186371, 
              61.07846853295523
            ], 
            [
              76.15796674998867, 
              61.06035594343692
            ], 
            [
              76.15372928254075, 
              61.054309800858775
            ], 
            [
              76.15145551951991, 
              61.053896389400435
            ], 
            [
              76.14453087759279, 
              61.05477488874939
            ], 
            [
              76.1425671731657, 
              61.054309800858775
            ], 
            [
              76.13595258983233, 
              61.02663707136648
            ], 
            [
              76.13140506379065, 
              61.020978502030516
            ], 
            [
              76.11114790233225, 
              61.017180284257066
            ], 
            [
              76.06629275910288, 
              61.022838853593015
            ], 
            [
              76.0426249531132, 
              61.020978502030516
            ], 
            [
              76.03621707550903, 
              61.02919505476493
            ], 
            [
              76.03146284373818, 
              61.06542023380152
            ], 
            [
              76.02898237498817, 
              61.07056203881457
            ], 
            [
              76.02536502472773, 
              61.0735075954552
            ], 
            [
              76.02205773306105, 
              61.07521291772083
            ], 
            [
              76.02030073436313, 
              61.076530666744276
            ], 
            [
              76.02216108592563, 
              61.083972072994314
            ], 
            [
              76.02691531769648, 
              61.089966539140164
            ], 
            [
              76.02836225780067, 
              61.09472077091101
            ], 
            [
              76.02030073436313, 
              61.09875153262978
            ], 
            [
              76.0026273945193, 
              61.09761465111936
            ], 
            [
              75.9981832213422, 
              61.09875153262978
            ], 
            [
              75.99714969269635, 
              61.10293732364542
            ], 
            [
              75.99911339712347, 
              61.11668325463506
            ], 
            [
              75.9981832213422, 
              61.12097239851529
            ], 
            [
              75.94257938019615, 
              61.15430369734355
            ], 
            [
              75.95425825389412, 
              61.173837388749874
            ], 
            [
              75.99187869660258, 
              61.177299709713424
            ]
          ]
        ]
      }, 
      "properties": {
        "ne:fid": 3727, 
        "ne:hasPlace": 20, 
        "hierarchy": [
          "woe:metropolitan-area=34821758", 
          "woe:region=20070526", 
          "woe:country=23424936"
        ], 
        "artisanal:foundry": "http://www.missionintegers.com/", 
        "ne:FeatureCla": "Urban area", 
        "placetype": "metropolitan-area", 
        "iso": "RU", 
        "longitude": 76.06814974959312, 
        "artisanal:id": 34821758, 
        "latitude": 61.15328597496089, 
        "woe:id": 34821758, 
        "ne:ScaleRank": 7
      }, 
      "id": 34821758
    }
  ], 
  "bbox": [
    75.94257938019615, 
    61.017180284257066, 
    76.16478803905122, 
    61.30987559675823
  ]
}