{
  "type": "FeatureCollection", 
  "features": [
    {
      "geometry": {
        "type": "Polygon", 
        "coordinates": [
          [
            [
              36.263450962068674, 
              36.84217011163432
            ], 
            [
              36.263450962068674, 
              36.84217011163432
            ], 
            [
              36.25859337743324, 
              36.83343679457698
            ], 
            [
              36.25828331883949, 
              36.83098216404312
            ], 
            [
              36.25911014175614, 
              36.82452261000664
            ], 
            [
              36.25859337743324, 
              36.82230052341808
            ], 
            [
              36.24743126805819, 
              36.82230052341808
            ], 
            [
              36.25766320165198, 
              36.791656399069
            ], 
            [
              36.25859337743324, 
              36.77791046807937
            ], 
            [
              36.24743126805819, 
              36.74457916925111
            ], 
            [
              36.24949832534986, 
              36.708224799133774
            ], 
            [
              36.24743126805819, 
              36.7000857610478
            ], 
            [
              36.23874962743315, 
              36.69114573826131
            ], 
            [
              36.2347188657144, 
              36.68393687595659
            ], 
            [
              36.23637251154773, 
              36.6778648951623
            ], 
            [
              36.245777622224836, 
              36.67814911553991
            ], 
            [
              36.24743126805819, 
              36.6778648951623
            ], 
            [
              36.24949832534986, 
              36.66117340753202
            ], 
            [
              36.24774132665195, 
              36.64339671482362
            ], 
            [
              36.23637251154773, 
              36.611202297505784
            ], 
            [
              36.233375278474796, 
              36.60874766697192
            ], 
            [
              36.22986128107894, 
              36.60815338800056
            ], 
            [
              36.22686404800601, 
              36.60629303643806
            ], 
            [
              36.219009230297644, 
              36.58546743422443
            ], 
            [
              36.20505659357886, 
              36.57378856052647
            ], 
            [
              36.169606561026626, 
              36.555650132792024
            ], 
            [
              36.182835727693345, 
              36.53549632419819
            ], 
            [
              36.24743126805819, 
              36.50009796807825
            ], 
            [
              36.24340050633941, 
              36.49389679620323
            ], 
            [
              36.23492557144354, 
              36.48991771091676
            ], 
            [
              36.224280226391414, 
              36.48826406508341
            ], 
            [
              36.21404829279763, 
              36.48896169691936
            ], 
            [
              36.20774376805804, 
              36.4908995631303
            ], 
            [
              36.206193475089265, 
              36.49291494398969
            ], 
            [
              36.205780063630925, 
              36.495757147765744
            ], 
            [
              36.20298953628716, 
              36.50009796807825
            ], 
            [
              36.17136355972454, 
              36.5137922226356
            ], 
            [
              36.153380161286975, 
              36.52634959568253
            ], 
            [
              36.147489048005696, 
              36.54453969984927
            ], 
            [
              36.141597934724416, 
              36.546684271789374
            ], 
            [
              36.08403038915128, 
              36.532524929341406
            ], 
            [
              36.073385044099155, 
              36.531982326802336
            ], 
            [
              36.06335981623454, 
              36.535134589172145
            ], 
            [
              36.05922570165117, 
              36.540198879536746
            ], 
            [
              36.16299197769325, 
              36.59337392836508
            ], 
            [
              36.17870161311001, 
              36.59634532322187
            ], 
            [
              36.18914025243296, 
              36.60401927341721
            ], 
            [
              36.201129184724664, 
              36.621950995422495
            ], 
            [
              36.211257765453865, 
              36.64241486261007
            ], 
            [
              36.21621870295388, 
              36.65778860121691
            ], 
            [
              36.2155985857664, 
              36.670475165344556
            ], 
            [
              36.21156782404762, 
              36.67993195245397
            ], 
            [
              36.20650353368302, 
              36.68874278415974
            ], 
            [
              36.20257612482885, 
              36.69936229099572
            ], 
            [
              36.20185265477676, 
              36.70631277113898
            ], 
            [
              36.20257612482885, 
              36.76920298923818
            ], 
            [
              36.19875206883924, 
              36.78457672784502
            ], 
            [
              36.188933546703794, 
              36.801784979798214
            ], 
            [
              36.12991906102647, 
              36.869274400371395
            ], 
            [
              36.107078077953446, 
              36.88774872491574
            ], 
            [
              36.125371534984794, 
              36.92580841729871
            ], 
            [
              36.1297123552973, 
              36.94317169854878
            ], 
            [
              36.12526818212021, 
              36.955677395163406
            ], 
            [
              36.11410607274516, 
              36.955677395163406
            ], 
            [
              36.12361453628685, 
              36.98223908136143
            ], 
            [
              36.13777387873483, 
              37.001772772767765
            ], 
            [
              36.15679080581825, 
              37.012108059226136
            ], 
            [
              36.180768670401676, 
              37.01122955987718
            ], 
            [
              36.18231896337042, 
              37.00921417901779
            ], 
            [
              36.18355919774544, 
              37.005570990541216
            ], 
            [
              36.186246372224616, 
              37.001979478496935
            ], 
            [
              36.191930779776726, 
              37.000093288718276
            ], 
            [
              36.20402306493301, 
              36.99846548110108
            ], 
            [
              36.217148878735145, 
              36.99257436781981
            ], 
            [
              36.22614057795394, 
              36.9792935247208
            ], 
            [
              36.22521040217268, 
              36.955677395163406
            ], 
            [
              36.19854536311007, 
              36.95733104099675
            ], 
            [
              36.1780814959225, 
              36.95280935317122
            ], 
            [
              36.147489048005696, 
              36.93340485284561
            ], 
            [
              36.16185509618285, 
              36.92286286065807
            ], 
            [
              36.179941847485, 
              36.91591238051481
            ], 
            [
              36.19286095555796, 
              36.90384593357466
            ], 
            [
              36.191930779776726, 
              36.87785268813185
            ], 
            [
              36.20381635920384, 
              36.882503567038114
            ], 
            [
              36.21094770686011, 
              36.89206370701211
            ], 
            [
              36.21962934748515, 
              36.90004771580121
            ], 
            [
              36.23637251154773, 
              36.900073554017354
            ], 
            [
              36.250635206860295, 
              36.87320180922558
            ], 
            [
              36.25859337743324, 
              36.86676809340524
            ], 
            [
              36.26438113784991, 
              36.85849986423854
            ], 
            [
              36.26572472508951, 
              36.850438340801006
            ], 
            [
              36.263450962068674, 
              36.84217011163432
            ]
          ]
        ]
      }, 
      "properties": {
        "ne:fid": 6939, 
        "ne:hasPlace": 20, 
        "hierarchy": [
          "woe:metropolitan-area=34823896", 
          "woe:region=2347286", 
          "woe:country=23424969"
        ], 
        "artisanal:foundry": "http://www.missionintegers.com/", 
        "ne:FeatureCla": "Urban area", 
        "placetype": "metropolitan-area", 
        "iso": "TR", 
        "longitude": 36.190097635488726, 
        "artisanal:id": 34823896, 
        "latitude": 36.77629008042106, 
        "woe:id": 34823896, 
        "ne:ScaleRank": 7
      }, 
      "id": 34823896
    }
  ], 
  "bbox": [
    36.05922570165117, 
    36.48826406508341, 
    36.26572472508951, 
    37.012108059226136
  ]
}