{
  "type": "FeatureCollection", 
  "features": [
    {
      "geometry": {
        "type": "Polygon", 
        "coordinates": [
          [
            [
              79.80146528515951, 
              28.651533108020814
            ], 
            [
              79.80146528515951, 
              28.651533108020814
            ], 
            [
              79.82420291536792, 
              28.656519883736976
            ], 
            [
              79.85303836458678, 
              28.655486355091142
            ], 
            [
              79.84652713411802, 
              28.629363918567606
            ], 
            [
              79.82595991406586, 
              28.614248562122228
            ], 
            [
              79.7995015807324, 
              28.611406358346173
            ], 
            [
              79.77521365755524, 
              28.622155056262883
            ], 
            [
              79.78503217969069, 
              28.64016429291661
            ], 
            [
              79.80146528515951, 
              28.651533108020814
            ]
          ]
        ]
      }, 
      "id": 37183716, 
      "properties": {
        "ne:fid": 8738, 
        "ne:hasPlace": 20, 
        "artisanal:foundry": "http://www.londonintegers.com/", 
        "ne:FeatureCla": "Urban area", 
        "placetype": "metropolitan-area", 
        "artisanal:id": 37183716, 
        "woe:id": 37183716, 
        "ne:ScaleRank": 7
      }
    }
  ], 
  "bbox": [
    79.77521365755524, 
    28.611406358346173, 
    79.85303836458678, 
    28.656519883736976
  ]
}