{
  "type": "FeatureCollection", 
  "features": [
    {
      "geometry": {
        "type": "Polygon", 
        "coordinates": [
          [
            [
              29.415186801885028, 
              -0.756387627773904
            ], 
            [
              29.415186801885028, 
              -0.756387627773904
            ], 
            [
              29.4064018083954, 
              -0.753597100430142
            ], 
            [
              29.391622348759938, 
              -0.737163994961335
            ], 
            [
              29.381907179489048, 
              -0.734115085456111
            ], 
            [
              29.390692172978675, 
              -0.723469740403985
            ], 
            [
              29.402887810999545, 
              -0.716286716315409
            ], 
            [
              29.418494093551715, 
              -0.71241098389352
            ], 
            [
              29.4375110206351, 
              -0.711945896002902
            ], 
            [
              29.436994256312204, 
              -0.725330091966498
            ], 
            [
              29.431309848760094, 
              -0.733598321133186
            ], 
            [
              29.415186801885028, 
              -0.745277194831161
            ], 
            [
              29.415186801885028, 
              -0.756387627773904
            ]
          ]
        ]
      }, 
      "props": {
        "ne:fid": 8117, 
        "ne:hasPlace": -1, 
        "hierarchy": [
          "woe:metropolitan-area=34824676", 
          "woe:region=20069830", 
          "woe:country=23424780"
        ], 
        "artisanal:foundry": "http://www.missionintegers.com/", 
        "ne:FeatureCla": "Urban area", 
        "placetype": "metropolitan-area", 
        "iso": "CD", 
        "longitude": 29.412121391550738, 
        "artisanal:id": 34824676, 
        "latitude": -0.7300314839097454, 
        "woe:id": 34824676, 
        "ne:ScaleRank": 7
      }, 
      "id": 34824676, 
      "properties": {
        "ne:fid": 8117, 
        "ne:hasPlace": -1, 
        "hierarchy": [
          "woe:metropolitan-area=34824676", 
          "woe:region=20069830", 
          "woe:country=23424780"
        ], 
        "artisanal:foundry": "http://www.missionintegers.com/", 
        "ne:FeatureCla": "Urban area", 
        "placetype": "metropolitan-area", 
        "iso": "CD", 
        "longitude": 29.412121391550738, 
        "artisanal:id": 34824676, 
        "latitude": -0.7300314839097454, 
        "woe:id": 34824676, 
        "ne:ScaleRank": 7
      }
    }
  ], 
  "bbox": [
    29.381907179489048, 
    -0.756387627773904, 
    29.4375110206351, 
    -0.711945896002902
  ]
}