{
  "type": "FeatureCollection", 
  "features": [
    {
      "geometry": {
        "type": "Polygon", 
        "coordinates": [
          [
            [
              106.66566531781905, 
              33.14774445243984
            ], 
            [
              106.66566531781905, 
              33.14774445243984
            ], 
            [
              106.65708703005859, 
              33.16141286878104
            ], 
            [
              106.65357303266276, 
              33.18006806083841
            ], 
            [
              106.66266808474612, 
              33.17533966728371
            ], 
            [
              106.67703413292327, 
              33.16190379488782
            ], 
            [
              106.68685265505871, 
              33.15784719495291
            ], 
            [
              106.68468224490246, 
              33.17448700615088
            ], 
            [
              106.68023807172537, 
              33.183168646775925
            ], 
            [
              106.67920454307952, 
              33.19029999443221
            ], 
            [
              106.68685265505871, 
              33.202288926723924
            ], 
            [
              106.70359581912129, 
              33.19381399182805
            ], 
            [
              106.70959028526715, 
              33.17420278577329
            ], 
            [
              106.70690311078798, 
              33.15203359632007
            ], 
            [
              106.69791141156918, 
              33.13562632906741
            ], 
            [
              106.67920454307952, 
              33.13919200289554
            ], 
            [
              106.66566531781905, 
              33.14774445243984
            ]
          ]
        ]
      }, 
      "id": 35318585, 
      "properties": {
        "ne:fid": 10818, 
        "ne:hasPlace": -1, 
        "artisanal:foundry": "http://www.brooklynintegers.com/", 
        "ne:FeatureCla": "Urban area", 
        "placetype": "metropolitan-area", 
        "artisanal:id": 35318585, 
        "woe:id": 35318585, 
        "ne:ScaleRank": 7
      }
    }
  ], 
  "bbox": [
    106.65357303266276, 
    33.13562632906741, 
    106.70959028526715, 
    33.202288926723924
  ]
}