{
  "type": "FeatureCollection", 
  "features": [
    {
      "geometry": {
        "type": "Polygon", 
        "coordinates": [
          [
            [
              69.1604610533461, 
              28.10539073334415
            ], 
            [
              69.1604610533461, 
              28.10539073334415
            ], 
            [
              69.15074588407523, 
              28.09291087494566
            ], 
            [
              69.13265913277309, 
              28.088880113226892
            ], 
            [
              69.12656131376264, 
              28.110429185492606
            ], 
            [
              69.12955854683557, 
              28.126862290961427
            ], 
            [
              69.14227094917936, 
              28.13817942963334
            ], 
            [
              69.16593875516904, 
              28.144432277940666
            ], 
            [
              69.1604610533461, 
              28.10539073334415
            ]
          ]
        ]
      }, 
      "properties": {
        "ne:fid": 8776, 
        "ne:hasPlace": 15, 
        "hierarchy": [
          "woe:metropolitan-area=34825120", 
          "woe:region=2346499", 
          "woe:country=23424922"
        ], 
        "artisanal:foundry": "http://www.missionintegers.com/", 
        "ne:FeatureCla": "Urban area", 
        "placetype": "metropolitan-area", 
        "iso": "PK", 
        "longitude": 69.14597248471277, 
        "artisanal:id": 34825120, 
        "latitude": 28.11654660633952, 
        "woe:id": 34825120, 
        "ne:ScaleRank": 7
      }, 
      "id": 34825120
    }
  ], 
  "bbox": [
    69.12656131376264, 
    28.088880113226892, 
    69.16593875516904, 
    28.144432277940666
  ]
}