{
  "type": "FeatureCollection", 
  "features": [
    {
      "geometry": {
        "type": "Polygon", 
        "coordinates": [
          [
            [
              64.0198962746797, 
              67.46208405218648
            ], 
            [
              64.0198962746797, 
              67.46208405218648
            ], 
            [
              64.01648563014845, 
              67.46621816676985
            ], 
            [
              64.01121463405468, 
              67.46515879990785
            ], 
            [
              64.01906945176304, 
              67.49339997015535
            ], 
            [
              64.04211714056521, 
              67.50655162217363
            ], 
            [
              64.06909223822157, 
              67.51572418890545
            ], 
            [
              64.08903934108622, 
              67.53184723578052
            ], 
            [
              64.11136355983632, 
              67.51019481065022
            ], 
            [
              64.09958133327376, 
              67.49091950140534
            ], 
            [
              64.06878217962782, 
              67.47544240993393
            ], 
            [
              64.03353885280475, 
              67.46515879990785
            ], 
            [
              64.0320919127006, 
              67.46285919867087
            ], 
            [
              64.03105838405475, 
              67.45851837835836
            ], 
            [
              64.02847456244015, 
              67.4547201605849
            ], 
            [
              64.0223767434297, 
              67.45402252874895
            ], 
            [
              64.0198962746797, 
              67.46208405218648
            ]
          ]
        ]
      }, 
      "properties": {
        "ne:fid": 3659, 
        "ne:hasPlace": 15, 
        "hierarchy": [
          "woe:metropolitan-area=35313277", 
          "woe:region=2346874", 
          "woe:country=23424936"
        ], 
        "artisanal:foundry": "http://www.brooklynintegers.com/", 
        "ne:FeatureCla": "Urban area", 
        "placetype": "metropolitan-area", 
        "iso": "RU", 
        "longitude": 64.06062659747857, 
        "artisanal:id": 35313277, 
        "latitude": 67.49335783734665, 
        "woe:id": 35313277, 
        "ne:ScaleRank": 7
      }, 
      "id": 35313277
    }
  ], 
  "bbox": [
    64.01121463405468, 
    67.45402252874895, 
    64.11136355983632, 
    67.53184723578052
  ]
}