{
  "type": "FeatureCollection", 
  "features": [
    {
      "geometry": {
        "type": "Polygon", 
        "coordinates": [
          [
            [
              29.23483605318637, 
              -26.107191664333655
            ], 
            [
              29.23483605318637, 
              -26.107191664333655
            ], 
            [
              29.225327589644678, 
              -26.116545098578484
            ], 
            [
              29.202486606571682, 
              -26.115563246364935
            ], 
            [
              29.17086063000903, 
              -26.101403903916967
            ], 
            [
              29.17695844901948, 
              -26.088071384385664
            ], 
            [
              29.198042433394562, 
              -26.070294691677255
            ], 
            [
              29.20414025240501, 
              -26.05696217214595
            ], 
            [
              29.21230512870713, 
              -26.0598560523543
            ], 
            [
              29.21292524589464, 
              -26.082025241807514
            ], 
            [
              29.21530236178006, 
              -26.090345147406502
            ], 
            [
              29.2175761248009, 
              -26.090810235297134
            ], 
            [
              29.22408735526969, 
              -26.089776706651293
            ], 
            [
              29.226361118290527, 
              -26.090345147406502
            ], 
            [
              29.23483605318637, 
              -26.107191664333655
            ]
          ]
        ]
      }, 
      "properties": {
        "ne:fid": 8336, 
        "ne:hasPlace": -1, 
        "hierarchy": [
          "woe:metropolitan-area=35316745", 
          "woe:region=2346983", 
          "woe:country=23424942"
        ], 
        "artisanal:foundry": "http://www.brooklynintegers.com/", 
        "ne:FeatureCla": "Urban area", 
        "placetype": "metropolitan-area", 
        "iso": "ZA", 
        "longitude": 29.20341460998327, 
        "artisanal:id": 35316745, 
        "latitude": -26.093738021585747, 
        "woe:id": 35316745, 
        "ne:ScaleRank": 7
      }, 
      "id": 35316745
    }
  ], 
  "bbox": [
    29.17086063000903, 
    -26.116545098578484, 
    29.23483605318637, 
    -26.05696217214595
  ]
}