{
  "type": "FeatureCollection", 
  "features": [
    {
      "geometry": {
        "type": "Polygon", 
        "coordinates": [
          [
            [
              -46.96614579933198, 
              -24.258777357685638
            ], 
            [
              -46.96614579933198, 
              -24.258777357685638
            ], 
            [
              -46.95074622250901, 
              -24.262394707946065
            ], 
            [
              -46.9355016749829, 
              -24.272729994404443
            ], 
            [
              -46.93658688006104, 
              -24.273350111591945
            ], 
            [
              -46.96645585792574, 
              -24.299084974873296
            ], 
            [
              -46.988909267756554, 
              -24.331072686461965
            ], 
            [
              -46.990511237157605, 
              -24.336188653258866
            ], 
            [
              -47.020819464696785, 
              -24.328953952737997
            ], 
            [
              -47.034048631363504, 
              -24.313089288024393
            ], 
            [
              -47.03019873715776, 
              -24.29722462331079
            ], 
            [
              -47.017357143733236, 
              -24.296604506123288
            ], 
            [
              -47.00172502296495, 
              -24.301410414326433
            ], 
            [
              -46.989581061376356, 
              -24.301978855081643
            ], 
            [
              -46.97991756853777, 
              -24.293813978779525
            ], 
            [
              -46.97304460304295, 
              -24.28322031015969
            ], 
            [
              -46.96614579933198, 
              -24.258777357685638
            ]
          ]
        ]
      }, 
      "properties": {
        "ne:fid": 3257, 
        "ne:hasPlace": 15, 
        "hierarchy": [
          "woe:metropolitan-area=34821448", 
          "woe:region=2344868", 
          "woe:country=23424768"
        ], 
        "artisanal:foundry": "http://www.missionintegers.com/", 
        "ne:FeatureCla": "Urban area", 
        "placetype": "metropolitan-area", 
        "iso": "BR", 
        "longitude": -46.98803516290916, 
        "artisanal:id": 34821448, 
        "latitude": -24.30145138948403, 
        "woe:id": 34821448, 
        "ne:ScaleRank": 7
      }, 
      "id": 34821448
    }
  ], 
  "bbox": [
    -47.034048631363504, 
    -24.336188653258866, 
    -46.9355016749829, 
    -24.258777357685638
  ]
}