{
  "type": "FeatureCollection", 
  "features": [
    {
      "geometry": {
        "type": "Polygon", 
        "coordinates": [
          [
            [
              -0.32276546874175, 
              52.08446971293226
            ], 
            [
              -0.32276546874175, 
              52.08446971293226
            ], 
            [
              -0.346381598299132, 
              52.11968720153918
            ], 
            [
              -0.346381598299132, 
              52.17826243754202
            ], 
            [
              -0.31687435546047, 
              52.17242300069303
            ], 
            [
              -0.235277268871613, 
              52.17826243754202
            ], 
            [
              -0.23393368163201, 
              52.163586330771125
            ], 
            [
              -0.243571336254462, 
              52.14379425720334
            ], 
            [
              -0.246336025382078, 
              52.133820705771
            ], 
            [
              -0.242098557934128, 
              52.11774933532823
            ], 
            [
              -0.233882005199717, 
              52.10472687439068
            ], 
            [
              -0.229179449861164, 
              52.09237620707292
            ], 
            [
              -0.235277268871613, 
              52.07826854105724
            ], 
            [
              -0.283258836254618, 
              52.07111135518481
            ], 
            [
              -0.32276546874175, 
              52.08446971293226
            ]
          ]
        ]
      }, 
      "props": {
        "ne:fid": 5796, 
        "ne:hasPlace": 15, 
        "hierarchy": [
          "woe:metropolitan-area=34823134", 
          "woe:region=24554868", 
          "woe:country=23424975"
        ], 
        "artisanal:foundry": "http://www.missionintegers.com/", 
        "ne:FeatureCla": "Urban area", 
        "placetype": "metropolitan-area", 
        "iso": "GB", 
        "longitude": -0.288608856720382, 
        "artisanal:id": 34823134, 
        "latitude": 52.127273434932704, 
        "woe:id": 34823134, 
        "ne:ScaleRank": 7
      }, 
      "id": 34823134, 
      "properties": {
        "ne:fid": 5796, 
        "ne:hasPlace": 15, 
        "hierarchy": [
          "woe:metropolitan-area=34823134", 
          "woe:region=24554868", 
          "woe:country=23424975"
        ], 
        "artisanal:foundry": "http://www.missionintegers.com/", 
        "ne:FeatureCla": "Urban area", 
        "placetype": "metropolitan-area", 
        "iso": "GB", 
        "longitude": -0.288608856720382, 
        "artisanal:id": 34823134, 
        "latitude": 52.127273434932704, 
        "woe:id": 34823134, 
        "ne:ScaleRank": 7
      }
    }
  ], 
  "bbox": [
    -0.346381598299132, 
    52.07111135518481, 
    -0.229179449861164, 
    52.17826243754202
  ]
}