{
  "type": "FeatureCollection", 
  "features": [
    {
      "geometry": {
        "type": "Polygon", 
        "coordinates": [
          [
            [
              -108.4218261381195, 
              45.84363617612344
            ], 
            [
              -108.4218261381195, 
              45.84363617612344
            ], 
            [
              -108.408106045346, 
              45.835135403011435
            ], 
            [
              -108.40702084026788, 
              45.82908926043328
            ], 
            [
              -108.41081905804133, 
              45.82647960060254
            ], 
            [
              -108.41606421591896, 
              45.82542023374056
            ], 
            [
              -108.41919064007261, 
              45.82402497006868
            ], 
            [
              -108.41960405153095, 
              45.819115709000954
            ], 
            [
              -108.4180537585622, 
              45.80611908627955
            ], 
            [
              -108.41919064007261, 
              45.80185578061547
            ], 
            [
              -108.42347978395284, 
              45.80066722267276
            ], 
            [
              -108.43655392132268, 
              45.80224335385765
            ], 
            [
              -108.44146318239041, 
              45.80185578061547
            ], 
            [
              -108.4422383288748, 
              45.80056386980817
            ], 
            [
              -108.45259945354931, 
              45.790719509456565
            ], 
            [
              -108.47479448121867, 
              45.779634914729954
            ], 
            [
              -108.475207892677, 
              45.777361151709115
            ], 
            [
              -108.47425187867961, 
              45.77053986264659
            ], 
            [
              -108.47479448121867, 
              45.76847280535492
            ], 
            [
              -108.47952287477338, 
              45.76782684995126
            ], 
            [
              -108.49282955608854, 
              45.76966136329763
            ], 
            [
              -108.49698950888803, 
              45.76847280535492
            ], 
            [
              -108.49722205283334, 
              45.76635407163094
            ], 
            [
              -108.49667945029428, 
              45.759145209326235
            ], 
            [
              -108.49698950888803, 
              45.75738821062831
            ], 
            [
              -108.5076606921563, 
              45.75601878517257
            ], 
            [
              -108.53057918987776, 
              45.75829254819341
            ], 
            [
              -108.54140540244289, 
              45.75738821062831
            ], 
            [
              -108.54287818076321, 
              45.75539866798508
            ], 
            [
              -108.54419592978665, 
              45.751781317724635
            ], 
            [
              -108.54690894248198, 
              45.748112291031916
            ], 
            [
              -108.5525416736018, 
              45.7462519394694
            ], 
            [
              -108.60184099000824, 
              45.748732408219425
            ], 
            [
              -108.61917843304217, 
              45.75738821062831
            ], 
            [
              -108.61530270062028, 
              45.76599233660491
            ], 
            [
              -108.61333899619318, 
              45.80095144305035
            ], 
            [
              -108.60809383831555, 
              45.812940375342066
            ], 
            [
              -108.58375423870609, 
              45.803018500342034
            ], 
            [
              -108.5747625394873, 
              45.80185578061547
            ], 
            [
              -108.56781205934405, 
              45.80549896909204
            ], 
            [
              -108.56685604534664, 
              45.81162262631862
            ], 
            [
              -108.56703691285966, 
              45.81839223894886
            ], 
            [
              -108.56367794476068, 
              45.82402497006868
            ], 
            [
              -108.55380774619294, 
              45.82604035092807
            ], 
            [
              -108.529209764422, 
              45.82226797137075
            ], 
            [
              -108.51923621298968, 
              45.82402497006868
            ], 
            [
              -108.4948966133802, 
              45.85652944598027
            ], 
            [
              -108.48587907594528, 
              45.857356268896936
            ], 
            [
              -108.48616329632289, 
              45.84797699643596
            ], 
            [
              -108.48587907594528, 
              45.846271674170325
            ], 
            [
              -108.4218261381195, 
              45.84363617612344
            ]
          ]
        ]
      }, 
      "props": {
        "ne:fid": 1055, 
        "ne:hasPlace": 20, 
        "hierarchy": [
          "woe:metropolitan-area=35311323", 
          "woe:region=2347585", 
          "woe:country=23424977"
        ], 
        "artisanal:foundry": "http://www.brooklynintegers.com/", 
        "ne:FeatureCla": "Urban area", 
        "placetype": "metropolitan-area", 
        "iso": "US", 
        "longitude": -108.51819619055439, 
        "artisanal:id": 35311323, 
        "latitude": 45.79763026167786, 
        "woe:id": 35311323, 
        "ne:ScaleRank": 7
      }, 
      "id": 35311323, 
      "properties": {
        "ne:fid": 1055, 
        "ne:hasPlace": 20, 
        "hierarchy": [
          "woe:metropolitan-area=35311323", 
          "woe:region=2347585", 
          "woe:country=23424977"
        ], 
        "artisanal:foundry": "http://www.brooklynintegers.com/", 
        "ne:FeatureCla": "Urban area", 
        "placetype": "metropolitan-area", 
        "iso": "US", 
        "longitude": -108.51819619055439, 
        "artisanal:id": 35311323, 
        "latitude": 45.79763026167786, 
        "woe:id": 35311323, 
        "ne:ScaleRank": 7
      }
    }
  ], 
  "bbox": [
    -108.61917843304217, 
    45.7462519394694, 
    -108.40702084026788, 
    45.857356268896936
  ]
}