{
  "type": "FeatureCollection", 
  "features": [
    {
      "geometry": {
        "type": "Polygon", 
        "coordinates": [
          [
            [
              35.800430128733495, 
              27.385124620060026
            ], 
            [
              35.800430128733495, 
              27.385124620060026
            ], 
            [
              35.817896762848136, 
              27.381998195906363
            ], 
            [
              35.82533816909816, 
              27.377631537377695
            ], 
            [
              35.819757114410635, 
              27.364557400007854
            ], 
            [
              35.75857221857706, 
              27.33321564382284
            ], 
            [
              35.755161574045815, 
              27.32533498789833
            ], 
            [
              35.75505822118123, 
              27.319366359968612
            ], 
            [
              35.75330122248329, 
              27.314689642846204
            ], 
            [
              35.74513634618117, 
              27.31063304291129
            ], 
            [
              35.74110558446242, 
              27.31037466074983
            ], 
            [
              35.733250766754054, 
              27.31228668874462
            ], 
            [
              35.72953006362903, 
              27.312441718041498
            ], 
            [
              35.7246724789936, 
              27.31076223399201
            ], 
            [
              35.71743777847274, 
              27.306214707950332
            ], 
            [
              35.699971144358074, 
              27.32479238535926
            ], 
            [
              35.652635532378724, 
              27.35383454030729
            ], 
            [
              35.64033654149327, 
              27.36344635671358
            ], 
            [
              35.616668735503566, 
              27.389672146101702
            ], 
            [
              35.61294803237857, 
              27.395046495060058
            ], 
            [
              35.61305138524315, 
              27.395124009708496
            ], 
            [
              35.622973260243185, 
              27.404296576440302
            ], 
            [
              35.64447065607661, 
              27.417060655216403
            ], 
            [
              35.68157433446217, 
              27.41747406667473
            ], 
            [
              35.69190962092054, 
              27.422099107364858
            ], 
            [
              35.69190962092054, 
              27.43318370209147
            ], 
            [
              35.702761671701836, 
              27.432408555607083
            ], 
            [
              35.725292596181106, 
              27.422099107364858
            ], 
            [
              35.75939904149374, 
              27.423856106062786
            ], 
            [
              35.76973432795211, 
              27.422099107364858
            ], 
            [
              35.773455031077134, 
              27.418300889591407
            ], 
            [
              35.78089643732716, 
              27.399878241479357
            ], 
            [
              35.78306684748341, 
              27.399335638940286
            ], 
            [
              35.789681430816785, 
              27.40036916758612
            ], 
            [
              35.79195519383762, 
              27.399878241479357
            ], 
            [
              35.79236860529596, 
              27.39763031667465
            ], 
            [
              35.7914384295147, 
              27.390783189395975
            ], 
            [
              35.79195519383762, 
              27.3887678085366
            ], 
            [
              35.800430128733495, 
              27.385124620060026
            ]
          ]
        ]
      }, 
      "properties": {
        "ne:fid": 9559, 
        "ne:hasPlace": 15, 
        "hierarchy": [
          "woe:metropolitan-area=37186290", 
          "woe:region=2346962", 
          "woe:country=23424938"
        ], 
        "artisanal:foundry": "http://www.londonintegers.com/", 
        "ne:FeatureCla": "Urban area", 
        "placetype": "metropolitan-area", 
        "iso": "SA", 
        "longitude": 35.718111585637565, 
        "artisanal:id": 37186290, 
        "latitude": 27.37528519291425, 
        "woe:id": 37186290, 
        "ne:ScaleRank": 7
      }, 
      "id": 37186290
    }
  ], 
  "bbox": [
    35.61294803237857, 
    27.306214707950332, 
    35.82533816909816, 
    27.43318370209147
  ]
}