{
  "type": "FeatureCollection", 
  "features": [
    {
      "geometry": {
        "type": "Polygon", 
        "coordinates": [
          [
            [
              -47.88942277687474, 
              -22.05787810637475
            ], 
            [
              -47.88942277687474, 
              -22.05787810637475
            ], 
            [
              -47.88942277687474, 
              -22.068988539317502
            ], 
            [
              -47.912082892434725, 
              -22.05761972421329
            ], 
            [
              -47.92921362973949, 
              -22.03266000741631
            ], 
            [
              -47.94034990089838, 
              -22.00082732512452
            ], 
            [
              -47.94497494158851, 
              -21.96904631926502
            ], 
            [
              -47.9351822576692, 
              -21.96770273202543
            ], 
            [
              -47.90931820330712, 
              -21.97137175871815
            ], 
            [
              -47.90050737160135, 
              -21.96904631926502
            ], 
            [
              -47.90050737160135, 
              -21.957884209889976
            ], 
            [
              -47.8922133042185, 
              -21.961036472259778
            ], 
            [
              -47.87833818214814, 
              -21.98015675220777
            ], 
            [
              -47.85242245135376, 
              -22.004651381114115
            ], 
            [
              -47.84255225278602, 
              -22.023978366791276
            ], 
            [
              -47.84495520688759, 
              -22.046767673431994
            ], 
            [
              -47.850536261575115, 
              -22.05219369882264
            ], 
            [
              -47.88076697446586, 
              -22.05803313567162
            ], 
            [
              -47.887329881366924, 
              -22.057309665619535
            ], 
            [
              -47.88942277687474, 
              -22.05787810637475
            ]
          ]
        ]
      }, 
      "properties": {
        "ne:fid": 3161, 
        "ne:hasPlace": 20, 
        "hierarchy": [
          "woe:metropolitan-area=35312925", 
          "woe:region=2344868", 
          "woe:country=23424768"
        ], 
        "artisanal:foundry": "http://www.brooklynintegers.com/", 
        "ne:FeatureCla": "Urban area", 
        "placetype": "metropolitan-area", 
        "iso": "BR", 
        "longitude": -47.89462311290216, 
        "artisanal:id": 35312925, 
        "latitude": -22.014049409831365, 
        "woe:id": 35312925, 
        "ne:ScaleRank": 7
      }, 
      "id": 35312925
    }
  ], 
  "bbox": [
    -47.94497494158851, 
    -22.068988539317502, 
    -47.84255225278602, 
    -21.957884209889976
  ]
}